tests/__init__.py
tests/test_agent_registration.py
tests/test_envs.py
tests/test_history.py
tests/test_plot.py
tests/test_single_interaction_step.py
tests/test_time_period_step.py
tests/test_run/__init__.py
tests/test_run/test_interface.py
tests/test_run/test_simulation.py
tests/test_run/test_store.py
truman/__init__.py
truman/_version.py
truman/agent_registration.py
truman/errors.py
truman/history.py
truman/plot.py
truman/single_interaction_step.py
truman/time_period_step.py
truman/typing.py
truman/run/__init__.py
truman/run/interface.py
truman/run/simulation.py
truman/run/store.py
truman-0.0.1a1.dist-info/LICENSE.txt
truman-0.0.1a1.dist-info/METADATA
truman-0.0.1a1.dist-info/WHEEL
truman-0.0.1a1.dist-info/top_level.txt
truman-0.0.1a1.dist-info/RECORD
