Metadata-Version: 2.1
Name: truman
Version: 0.0.1a1
Summary: Simulating customer interactions with products and bid auctions at large scale.
Home-page: https://github.com/datavaluepeople/truman
Author: datavaluepeople
License: MIT
Platform: UNKNOWN
Requires-Python: >=3.7
Requires-Dist: numpy
Requires-Dist: gym
Requires-Dist: pandas
Requires-Dist: pyarrow
